<?xml version="1.0" ?>
 <Level width="2">
  <Camera x="0" y="1" minWidth="20" maxWidth="30"/>
  <Birds>
   <Bird type="BirdRed"/>
   <Bird type="BirdRed"/>
   <Bird type="BirdRed"/>
  </Birds>
  <Slingshot x="-8" y="-2.5"/>
  <GameObjects>
   <Block type="SquareTiny" material="wood" x="2.0549999999999997" y="-3.39" rotation="0.0"/>
   <Block type="SquareTiny" material="stone" x="3.245" y="-3.39" rotation="0.0"/>
   <Block type="SquareTiny" material="wood" x="3.035" y="-0.23999999999999982" rotation="0.0"/>
   <Block type="RectTiny" material="wood" x="3.3149999999999995" y="-2.69" rotation="90.0"/>
   <Block type="RectTiny" material="ice" x="3.5949999999999998" y="-3.1799999999999997" rotation="0.0"/>
   <Block type="RectTiny" material="wood" x="3.035" y="-0.5899999999999999" rotation="90.0"/>
   <Block type="RectTiny" material="ice" x="3.9450000000000003" y="-0.37999999999999995" rotation="90.0"/>
   <Block type="RectTiny" material="wood" x="4.925" y="-2.9699999999999998" rotation="0.0"/>
   <Block type="RectSmall" material="wood" x="1.4949999999999999" y="-3.39" rotation="0.0"/>
   <Block type="RectSmall" material="stone" x="3.875" y="-3.39" rotation="0.0"/>
   <Block type="RectSmall" material="wood" x="3.875" y="-2.76" rotation="0.0"/>
   <Block type="RectSmall" material="ice" x="4.785" y="-2.34" rotation="90.0"/>
   <Block type="RectMedium" material="ice" x="4.6450000000000005" y="-0.94" rotation="90.0"/>
   <Block type="RectMedium" material="wood" x="6.115" y="-3.39" rotation="0.0"/>
   <Block type="RectBig" material="ice" x="2.4050000000000002" y="-3.1799999999999997" rotation="0.0"/>
   <Block type="RectBig" material="wood" x="3.035" y="-1.78" rotation="90.0"/>
   <Block type="RectBig" material="wood" x="3.7350000000000003" y="-2.9699999999999998" rotation="0.0"/>
   <Block type="RectBig" material="wood" x="3.9450000000000003" y="-1.57" rotation="90.0"/>
   <Block type="RectBig" material="wood" x="3.7350000000000003" y="-0.029999999999999846" rotation="0.0"/>
   <Block type="RectBig" material="ice" x="5.065" y="-3.1799999999999997" rotation="0.0"/>
   <Pig type="BasicSmall" material="None" x="3.3149999999999995" y="0.24999999999999994" rotation="0.0"/>
   <Pig type="BasicSmall" material="None" x="3.9450000000000003" y="0.3199999999999998" rotation="0.0"/>
   <Pig type="BasicSmall" material="None" x="5.485" y="-2.83" rotation="0.0"/>
   <Pig type="BasicSmall" material="None" x="4.575" y="0.24999999999999994" rotation="0.0"/>
  </GameObjects>
 </Level>
