<?xml version="1.0" ?>
 <Level width="2">
  <Camera x="0" y="1" minWidth="20" maxWidth="30"/>
  <Birds>
   <Bird type="BirdRed"/>
   <Bird type="BirdRed"/>
   <Bird type="BirdRed"/>
  </Birds>
  <Slingshot x="-8" y="-2.5"/>
  <GameObjects>
   <Block type="SquareHole" material="ice" x="3.34" y="-2.41" rotation="0.0"/>
   <Block type="SquareHole" material="ice" x="5.16" y="-2.41" rotation="0.0"/>
   <Block type="RectFat" material="wood" x="2.5700000000000003" y="-3.04" rotation="0.0"/>
   <Block type="RectFat" material="wood" x="4.32" y="-3.25" rotation="0.0"/>
   <Block type="RectFat" material="ice" x="5.93" y="-3.11" rotation="0.0"/>
   <Block type="SquareTiny" material="wood" x="2.01" y="-3.1799999999999997" rotation="0.0"/>
   <Block type="SquareTiny" material="wood" x="3.13" y="-3.1799999999999997" rotation="0.0"/>
   <Block type="SquareTiny" material="wood" x="3.55" y="-3.1799999999999997" rotation="0.0"/>
   <Block type="SquareTiny" material="ice" x="4.53" y="-2.41" rotation="0.0"/>
   <Block type="SquareTiny" material="stone" x="4.6" y="-2.76" rotation="0.0"/>
   <Block type="SquareTiny" material="stone" x="5.72" y="-2.76" rotation="0.0"/>
   <Block type="RectTiny" material="stone" x="3.55" y="-1.71" rotation="0.0"/>
   <Block type="RectSmall" material="stone" x="4.18" y="-2.2" rotation="0.0"/>
   <Block type="RectBig" material="ice" x="2.71" y="-3.39" rotation="0.0"/>
   <Block type="RectBig" material="wood" x="4.25" y="-1.92" rotation="0.0"/>
   <Block type="RectBig" material="ice" x="5.72" y="-3.39" rotation="0.0"/>
   <Block type="RectTiny" material="ice" x="2.5" y="-3.3899999999999997" rotation="0.0"/>
   <Block type="SquareTiny" material="wood" x="4.04" y="-2.4" rotation="0.0"/>
   <Block type="SquareTiny" material="ice" x="4.46" y="-2.4" rotation="0.0"/>
   <Block type="RectTiny" material="wood" x="4.25" y="-1.2799999999999994" rotation="0.0"/>
   <Block type="RectSmall" material="ice" x="4.04" y="-1.7699999999999996" rotation="90.0"/>
   <Block type="RectBig" material="ice" x="4.25" y="-2.4699999999999998" rotation="90.0"/>
  </GameObjects>
 </Level>
