<?xml version="1.0" ?>
 <Level width="2">
  <Camera x="0" y="1" minWidth="20" maxWidth="30"/>
  <Birds>
   <Bird type="BirdRed"/>
   <Bird type="BirdRed"/>
   <Bird type="BirdRed"/>
  </Birds>
  <Slingshot x="-8" y="-2.5"/>
  <GameObjects>
   <Block type="SquareHole" material="wood" x="4.1899999999999995" y="0.285" rotation="0.0"/>
   <Block type="SquareHole" material="wood" x="5.24" y="0.07500000000000001" rotation="0.0"/>
   <Block type="SquareHole" material="wood" x="5.17" y="0.9149999999999998" rotation="0.0"/>
   <Block type="RectFat" material="wood" x="2.02" y="-3.005" rotation="90.0"/>
   <Block type="RectFat" material="wood" x="3.98" y="-3.005" rotation="90.0"/>
   <Block type="RectFat" material="wood" x="4.539999999999999" y="-3.005" rotation="90.0"/>
   <Block type="RectFat" material="ice" x="2.9299999999999997" y="0.285" rotation="90.0"/>
   <Block type="RectFat" material="ice" x="3.42" y="0.3549999999999998" rotation="90.0"/>
   <Block type="RectFat" material="ice" x="4.1899999999999995" y="1.1249999999999998" rotation="0.0"/>
   <Block type="SquareSmall" material="stone" x="3.42" y="0.9850000000000001" rotation="0.0"/>
   <Block type="SquareTiny" material="wood" x="2.1599999999999997" y="-2.445" rotation="0.0"/>
   <Block type="SquareTiny" material="wood" x="2.3699999999999997" y="-3.355" rotation="0.0"/>
   <Block type="SquareTiny" material="wood" x="4.049999999999999" y="-2.445" rotation="0.0"/>
   <Block type="SquareTiny" material="wood" x="3.0" y="0.8449999999999995" rotation="0.0"/>
   <Block type="SquareTiny" material="wood" x="4.68" y="-0.2750000000000001" rotation="0.0"/>
   <Block type="SquareTiny" material="wood" x="5.52" y="-0.48500000000000004" rotation="0.0"/>
   <Block type="RectTiny" material="wood" x="4.539999999999999" y="-2.445" rotation="0.0"/>
   <Block type="RectSmall" material="wood" x="1.6699999999999997" y="-3.0749999999999997" rotation="90.0"/>
   <Block type="RectSmall" material="wood" x="2.1599999999999997" y="-1.815" rotation="90.0"/>
   <Block type="RectSmall" material="stone" x="5.52" y="-1.115" rotation="90.0"/>
   <Block type="RectBig" material="wood" x="1.9499999999999997" y="-1.3950000000000002" rotation="90.0"/>
   <Block type="RectBig" material="wood" x="2.9299999999999997" y="-0.2750000000000001" rotation="0.0"/>
   <Block type="RectBig" material="ice" x="3.8399999999999994" y="-1.465" rotation="90.0"/>
   <Block type="RectBig" material="stone" x="4.470000000000001" y="-1.325" rotation="90.0"/>
   <Pig type="BasicSmall" material="None" x="5.029999999999999" y="-3.215" rotation="0.0"/>
   <Pig type="BasicSmall" material="None" x="3.63" y="1.4750000000000003" rotation="0.0"/>
   <Block type="SquareHole" material="wood" x="6.289999999999999" y="-3.075" rotation="0.0"/>
   <Block type="RectSmall" material="wood" x="6.359999999999999" y="-2.515" rotation="0.0"/>
   <Block type="RectBig" material="wood" x="6.43" y="-1.395" rotation="90.0"/>
  </GameObjects>
 </Level>
