<?xml version="1.0" ?>
 <Level width="2">
  <Camera x="0" y="1" minWidth="20" maxWidth="30"/>
  <Birds>
   <Bird type="BirdRed"/>
   <Bird type="BirdRed"/>
   <Bird type="BirdRed"/>
  </Birds>
  <Slingshot x="-8" y="-2.5"/>
  <GameObjects>
   <Block type="SquareHole" material="stone" x="1.9149999999999998" y="-2.96" rotation="0.0"/>
   <Block type="SquareHole" material="wood" x="1.9149999999999998" y="-2.12" rotation="0.0"/>
   <Block type="SquareHole" material="wood" x="2.8949999999999996" y="-2.96" rotation="0.0"/>
   <Block type="SquareHole" material="ice" x="2.2649999999999997" y="-1.2799999999999998" rotation="0.0"/>
   <Block type="SquareHole" material="stone" x="2.8949999999999996" y="-2.12" rotation="0.0"/>
   <Block type="SquareHole" material="ice" x="5.135" y="-1.2799999999999998" rotation="0.0"/>
   <Block type="SquareHole" material="ice" x="5.835" y="-2.96" rotation="0.0"/>
   <Block type="SquareHole" material="stone" x="6.115" y="-1.2799999999999998" rotation="0.0"/>
   <Block type="RectFat" material="ice" x="3.1049999999999995" y="-1.2799999999999998" rotation="90.0"/>
   <Block type="RectFat" material="ice" x="4.2250000000000005" y="-1.0699999999999998" rotation="90.0"/>
   <Block type="RectFat" material="ice" x="6.675" y="-2.96" rotation="90.0"/>
   <Block type="SquareSmall" material="wood" x="3.7350000000000003" y="-1.0699999999999998" rotation="0.0"/>
   <Block type="RectTiny" material="wood" x="4.855" y="-2.8899999999999997" rotation="0.0"/>
   <Block type="RectTiny" material="ice" x="4.575" y="-1.0" rotation="90.0"/>
   <Block type="RectTiny" material="ice" x="5.415" y="-2.26" rotation="90.0"/>
   <Block type="RectTiny" material="ice" x="5.695" y="-1.98" rotation="90.0"/>
   <Block type="RectTiny" material="wood" x="6.115" y="-2.33" rotation="90.0"/>
   <Block type="RectTiny" material="stone" x="6.325" y="-0.7199999999999999" rotation="0.0"/>
   <Block type="RectMedium" material="ice" x="4.155" y="-2.54" rotation="90.0"/>
   <Block type="RectMedium" material="stone" x="5.135" y="-2.54" rotation="90.0"/>
   <Block type="RectMedium" material="ice" x="6.3950000000000005" y="-2.54" rotation="90.0"/>
   <Block type="RectBig" material="wood" x="3.5249999999999995" y="-2.4" rotation="90.0"/>
   <Block type="RectBig" material="wood" x="3.8049999999999997" y="-2.4" rotation="90.0"/>
   <Block type="RectBig" material="ice" x="4.505" y="-2.4699999999999998" rotation="90.0"/>
  </GameObjects>
 </Level>
