<?xml version="1.0" encoding="utf-16"?>
<Level width ="2">
<Camera x="0" y="2" minWidth="20" maxWidth="30">
<Birds>
<Bird type="BirdRed"/>
<Bird type="BirdBlack"/>
<Bird type="BirdRed"/>
<Bird type="BirdBlue"/>
<Bird type="BirdBlack"/>
<Bird type="BirdRed"/>
</Birds>
<Slingshot x="-8" y="-2.5">
<GameObjects>
<Block type="RectBig" material="stone" x="-2.8312634441" y="-2.47" rotation="90" />
<Block type="RectBig" material="stone" x="-2.2012634441" y="-2.47" rotation="90" />
<Block type="RectBig" material="ice" x="-1.8562634441" y="-2.47" rotation="90" />
<Block type="RectBig" material="ice" x="-1.2262634441" y="-2.47" rotation="90" />
<Block type="RectBig" material="stone" x="-0.8812634441" y="-2.47" rotation="90" />
<Block type="RectBig" material="wood" x="-0.2512634441" y="-2.47" rotation="90" />
<Block type="RectTiny" material="wood" x="-2.8312634441" y="-1.225" rotation="90" />
<Block type="RectTiny" material="ice" x="-2.2012634441" y="-1.225" rotation="90" />
<Block type="RectTiny" material="stone" x="-1.8562634441" y="-1.225" rotation="90" />
<Block type="RectTiny" material="ice" x="-1.2262634441" y="-1.225" rotation="90" />
<Block type="RectTiny" material="ice" x="-0.8812634441" y="-1.225" rotation="90" />
<Block type="RectTiny" material="ice" x="-0.2512634441" y="-1.225" rotation="90" />
<Block type="RectFat" material="ice" x="-2.5162634441" y="-0.795" rotation="0" />
<Block type="RectFat" material="stone" x="-1.5412634441" y="-0.795" rotation="0" />
<Block type="RectFat" material="wood" x="-0.5662634441" y="-0.795" rotation="0" />
<Block type="RectSmall" material="ice" x="-2.5162634441" y="-0.47" rotation="0" />
<Block type="RectSmall" material="stone" x="-1.5412634441" y="-0.47" rotation="0" />
<Block type="RectSmall" material="stone" x="-0.5662634441" y="-0.47" rotation="0" />
<Block type="RectTiny" material="wood" x="-2.4112634441" y="-0.25" rotation="0" />
<Block type="RectTiny" material="wood" x="-1.5412634441" y="-0.25" rotation="0" />
<Block type="RectTiny" material="wood" x="-0.6712634441" y="-0.25" rotation="0" />
<Block type="RectFat" material="ice" x="0.544487068" y="-3.285" rotation="0" />
<Block type="RectFat" material="wood" x="1.884487068" y="-3.285" rotation="0" />
<Block type="RectTiny" material="stone" x="0.649487068" y="-2.96" rotation="0" />
<Block type="RectTiny" material="stone" x="1.779487068" y="-2.96" rotation="0" />
<Block type="RectBig" material="ice" x="4.0597132902" y="-3.39" rotation="0" />
<Block type="RectFat" material="wood" x="4.0597132902" y="-3.065" rotation="0" />
<Block type="RectFat" material="wood" x="4.059713290180277" y="-2.635" rotation="0" />
<Block type="RectSmall" material="ice" x="6.3839627781" y="-3.39" rotation="0" />
<Block type="RectSmall" material="stone" x="7.3039627781" y="-3.39" rotation="0" />
<Block type="RectSmall" material="ice" x="8.2239627781" y="-3.39" rotation="0" />
<Block type="RectSmall" material="wood" x="6.3839627781" y="-3.17" rotation="0" />
<Block type="RectSmall" material="ice" x="7.3039627781" y="-3.17" rotation="0" />
<Block type="RectSmall" material="wood" x="8.2239627781" y="-3.17" rotation="0" />
<Block type="RectBig" material="wood" x="7.3039627781" y="-2.95" rotation="0" />
<Block type="RectSmall" material="stone" x="6.9889627781" y="-2.415" rotation="90" />
<Block type="RectSmall" material="ice" x="7.6189627781" y="-2.415" rotation="90" />
<Block type="RectFat" material="ice" x="7.3039627781" y="-1.775" rotation="0" />
<Block type="RectTiny" material="ice" x="7.303962778086351" y="-1.45" rotation="0" />
<Block type="RectBig" material="stone" x="0.2904643044" y="2.3982992697" rotation="0" />
<Block type="RectMedium" material="wood" x="0.2904643044" y="2.6182992697" rotation="0" />
<Block type="RectSmall" material="wood" x="-0.0395356956" y="3.1532992697" rotation="90" />
<Block type="RectSmall" material="stone" x="0.2904643044" y="3.1532992697" rotation="90" />
<Block type="RectSmall" material="wood" x="0.6204643044" y="3.1532992697" rotation="90" />
<Block type="Circle" material="wood" x="-0.0395356956" y="3.9782992697" rotation="0" />
<Block type="Circle" material="wood" x="-2.4112634441" y="0.26" rotation="0" />
<Block type="TriangleHole" material="stone" x="7.3039627781" y="-0.93" rotation="0" />
<Block type="CircleSmall" material="ice" x="4.3430466235" y="-2.195" rotation="0" />
<Block type="CircleSmall" material="wood" x="6.6172961114" y="-2.615" rotation="0" />
<Block type="CircleSmall" material="stone" x="0.6204643044" y="3.8032992697" rotation="0" />
<Pig type="BasicSmall" material="" x="-0.6712634441" y="0.11" rotation="0" />
<Pig type="BasicSmall" material="" x="-1.5412634441" y="0.11" rotation="0" />
<Pig type="BasicSmall" material="" x="1.779487068" y="-2.6" rotation="0" />
<Pig type="BasicSmall" material="" x="0.649487068" y="-2.6" rotation="0" />
<Pig type="BasicSmall" material="" x="3.7763799568" y="-2.17" rotation="0" />
<Pig type="BasicSmall" material="" x="3.3730466235" y="-3.03" rotation="0" />
<Pig type="BasicSmall" material="" x="7.9906294448" y="-2.59" rotation="0" />
<Platform type="Platform" material="" x="-0.6395356955730302" y="1.9782992696669708" />
<Platform type="Platform" material="" x="-0.01953569557303031" y="1.9782992696669708" />
<Platform type="Platform" material="" x="0.6004643044269697" y="1.9782992696669708" />
<Platform type="Platform" material="" x="1.2204643044269696" y="1.9782992696669708" />
<TNT type="" material="" x="4.7463799569" y="-3.03" rotation="0" />
</GameObjects>
</Level>
