<?xml version="1.0" encoding="utf-8"?>
<Level width ="2">
<Camera x="0" y="0" minWidth="20" maxWidth="30"/><Birds>
<Bird type="BirdBlue"/>
<Bird type="BirdYellow"/>
<Bird type="BirdYellow"/>
</Birds>
<Slingshot x="-8" y="-2.5"/>
<GameObjects>
<Block type="SquareSmall" material="ice" x="-2.625" y="-3.285" rotation="0" />
<Block type="SquareSmall" material="stone" x="-1.895" y="-3.285" rotation="0" />
<Block type="SquareSmall" material="ice" x="-1.165" y="-3.285" rotation="0" />
<Block type="SquareSmall" material="wood" x="-0.73" y="-3.285" rotation="0" />
<Block type="SquareSmall" material="stone" x="0.0" y="-3.285" rotation="0" />
<Block type="SquareSmall" material="stone" x="0.73" y="-3.285" rotation="0" />
<Block type="SquareSmall" material="wood" x="1.165" y="-3.285" rotation="0" />
<Block type="SquareSmall" material="stone" x="1.895" y="-3.285" rotation="0" />
<Block type="SquareSmall" material="ice" x="2.625" y="-3.285" rotation="0" />
<Block type="RectFat" material="ice" x="-2.625" y="-2.645" rotation="90" />
<Block type="RectFat" material="wood" x="-1.895" y="-2.645" rotation="90" />
<Block type="RectFat" material="ice" x="-1.165" y="-2.645" rotation="90" />
<Block type="RectFat" material="wood" x="-0.73" y="-2.645" rotation="90" />
<Block type="RectFat" material="wood" x="0.0" y="-2.645" rotation="90" />
<Block type="RectFat" material="stone" x="0.73" y="-2.645" rotation="90" />
<Block type="RectFat" material="wood" x="1.165" y="-2.645" rotation="90" />
<Block type="RectFat" material="ice" x="1.895" y="-2.645" rotation="90" />
<Block type="RectFat" material="wood" x="2.625" y="-2.645" rotation="90" />
<Block type="RectMedium" material="ice" x="-1.895" y="-2.11" rotation="0" />
<Block type="RectMedium" material="wood" x="0.0" y="-2.11" rotation="0" />
<Block type="RectMedium" material="wood" x="1.895" y="-2.11" rotation="0" />
<Block type="RectTiny" material="wood" x="-1.895" y="-1.785" rotation="90" />
<Block type="RectTiny" material="stone" x="-1.265" y="-1.785" rotation="90" />
<Block type="RectTiny" material="wood" x="-0.315" y="-1.785" rotation="90" />
<Block type="RectTiny" material="stone" x="0.315" y="-1.785" rotation="90" />
<Block type="RectTiny" material="ice" x="1.265" y="-1.785" rotation="90" />
<Block type="RectTiny" material="stone" x="1.895" y="-1.785" rotation="90" />
<Block type="RectSmall" material="wood" x="-1.58" y="-1.46" rotation="0" />
<Block type="RectSmall" material="wood" x="0.0" y="-1.46" rotation="0" />
<Block type="RectSmall" material="ice" x="1.58" y="-1.46" rotation="0" />
<Block type="RectSmall" material="ice" x="-1.58" y="-1.24" rotation="0" />
<Block type="RectSmall" material="ice" x="0.0" y="-1.24" rotation="0" />
<Block type="RectSmall" material="wood" x="1.58" y="-1.24" rotation="0" />
<Block type="RectMedium" material="stone" x="-0.85" y="-1.02" rotation="0" />
<Block type="RectMedium" material="wood" x="0.85" y="-1.02" rotation="0" />
<Block type="RectSmall" material="wood" x="-1.275" y="-0.485" rotation="90" />
<Block type="RectSmall" material="stone" x="-0.85" y="-0.485" rotation="90" />
<Block type="RectSmall" material="stone" x="-0.425" y="-0.485" rotation="90" />
<Block type="RectSmall" material="wood" x="0.425" y="-0.485" rotation="90" />
<Block type="RectSmall" material="wood" x="0.85" y="-0.485" rotation="90" />
<Block type="RectSmall" material="stone" x="1.275" y="-0.485" rotation="90" />
<Block type="SquareTiny" material="ice" x="-1.275" y="0.05" rotation="0" />
<Block type="SquareTiny" material="wood" x="-0.85" y="0.05" rotation="0" />
<Block type="SquareTiny" material="wood" x="-0.425" y="0.05" rotation="0" />
<Block type="SquareTiny" material="wood" x="0.425" y="0.05" rotation="0" />
<Block type="SquareTiny" material="ice" x="0.85" y="0.05" rotation="0" />
<Block type="SquareTiny" material="wood" x="1.275" y="0.05" rotation="0" />
<Block type="SquareSmall" material="wood" x="-1.17" y="0.375" rotation="0" />
<Block type="SquareSmall" material="ice" x="-0.53" y="0.375" rotation="0" />
<Block type="SquareSmall" material="ice" x="0.53" y="0.375" rotation="0" />
<Block type="SquareSmall" material="stone" x="1.17" y="0.375" rotation="0" />
<Block type="RectSmall" material="ice" x="-1.17" y="1.015" rotation="90" />
<Block type="RectSmall" material="wood" x="-0.53" y="1.015" rotation="90" />
<Block type="RectSmall" material="wood" x="0.53" y="1.015" rotation="90" />
<Block type="RectSmall" material="stone" x="1.17" y="1.015" rotation="90" />
<Pig type="BasicSmall" material="" x="0.53" y="1.69" rotation="0" />
<Pig type="BasicSmall" material="" x="2.455" y="-1.75" rotation="0" />
<Pig type="BasicSmall" material="" x="-2.455" y="-1.75" rotation="0" />
<Pig type="BasicSmall" material="" x="-1.17" y="1.69" rotation="0" />
<TNT type="" material="" x="1.17" y="1.69" rotation="0" />
</GameObjects>
</Level>

