<?xml version="1.0" encoding="utf-8"?>
<Level width ="2">
<Camera x="0" y="0" minWidth="20" maxWidth="30"/><Birds>
<Bird type="BirdWhite"/>
<Bird type="BirdRed"/>
<Bird type="BirdRed"/>
</Birds>
<Slingshot x="-8" y="-2.5"/>
<GameObjects>
<Block type="RectFat" material="stone" x="-2.41" y="-3.285" rotation="0" />
<Block type="RectFat" material="stone" x="-1.47" y="-3.285" rotation="0" />
<Block type="RectFat" material="wood" x="-0.53" y="-3.285" rotation="0" />
<Block type="RectFat" material="wood" x="0.53" y="-3.285" rotation="0" />
<Block type="RectFat" material="ice" x="1.47" y="-3.285" rotation="0" />
<Block type="RectFat" material="ice" x="2.41" y="-3.285" rotation="0" />
<Block type="RectSmall" material="stone" x="-2.41" y="-2.96" rotation="0" />
<Block type="RectSmall" material="stone" x="-1.47" y="-2.96" rotation="0" />
<Block type="RectSmall" material="stone" x="-0.53" y="-2.96" rotation="0" />
<Block type="RectSmall" material="stone" x="0.53" y="-2.96" rotation="0" />
<Block type="RectSmall" material="wood" x="1.47" y="-2.96" rotation="0" />
<Block type="RectSmall" material="stone" x="2.41" y="-2.96" rotation="0" />
<Block type="RectFat" material="stone" x="-2.41" y="-2.635" rotation="0" />
<Block type="RectFat" material="stone" x="-1.47" y="-2.635" rotation="0" />
<Block type="RectFat" material="wood" x="-0.53" y="-2.635" rotation="0" />
<Block type="RectFat" material="ice" x="0.53" y="-2.635" rotation="0" />
<Block type="RectFat" material="ice" x="1.47" y="-2.635" rotation="0" />
<Block type="RectFat" material="wood" x="2.41" y="-2.635" rotation="0" />
<Block type="RectTiny" material="ice" x="-2.72" y="-2.205" rotation="90" />
<Block type="RectTiny" material="stone" x="-2.41" y="-2.205" rotation="90" />
<Block type="RectTiny" material="ice" x="-2.1" y="-2.205" rotation="90" />
<Block type="RectTiny" material="wood" x="-1.78" y="-2.205" rotation="90" />
<Block type="RectTiny" material="stone" x="-1.47" y="-2.205" rotation="90" />
<Block type="RectTiny" material="wood" x="-1.16" y="-2.205" rotation="90" />
<Block type="RectTiny" material="stone" x="-0.84" y="-2.205" rotation="90" />
<Block type="RectTiny" material="ice" x="-0.53" y="-2.205" rotation="90" />
<Block type="RectTiny" material="wood" x="-0.22" y="-2.205" rotation="90" />
<Block type="RectTiny" material="stone" x="0.22" y="-2.205" rotation="90" />
<Block type="RectTiny" material="wood" x="0.53" y="-2.205" rotation="90" />
<Block type="RectTiny" material="stone" x="0.84" y="-2.205" rotation="90" />
<Block type="RectTiny" material="wood" x="1.16" y="-2.205" rotation="90" />
<Block type="RectTiny" material="ice" x="1.47" y="-2.205" rotation="90" />
<Block type="RectTiny" material="wood" x="1.78" y="-2.205" rotation="90" />
<Block type="RectTiny" material="wood" x="2.1" y="-2.205" rotation="90" />
<Block type="RectTiny" material="wood" x="2.41" y="-2.205" rotation="90" />
<Block type="RectTiny" material="wood" x="2.72" y="-2.205" rotation="90" />
<Block type="RectMedium" material="ice" x="-2.72" y="-1.15" rotation="90" />
<Block type="RectMedium" material="ice" x="-2.41" y="-1.15" rotation="90" />
<Block type="RectMedium" material="stone" x="-2.1" y="-1.15" rotation="90" />
<Block type="RectMedium" material="stone" x="-1.78" y="-1.15" rotation="90" />
<Block type="RectMedium" material="ice" x="-1.47" y="-1.15" rotation="90" />
<Block type="RectMedium" material="stone" x="-1.16" y="-1.15" rotation="90" />
<Block type="RectMedium" material="wood" x="-0.84" y="-1.15" rotation="90" />
<Block type="RectMedium" material="wood" x="-0.53" y="-1.15" rotation="90" />
<Block type="RectMedium" material="wood" x="-0.22" y="-1.15" rotation="90" />
<Block type="RectMedium" material="ice" x="0.22" y="-1.15" rotation="90" />
<Block type="RectMedium" material="stone" x="0.53" y="-1.15" rotation="90" />
<Block type="RectMedium" material="ice" x="0.84" y="-1.15" rotation="90" />
<Block type="RectMedium" material="stone" x="1.16" y="-1.15" rotation="90" />
<Block type="RectMedium" material="wood" x="1.47" y="-1.15" rotation="90" />
<Block type="RectMedium" material="ice" x="1.78" y="-1.15" rotation="90" />
<Block type="RectMedium" material="ice" x="2.1" y="-1.15" rotation="90" />
<Block type="RectMedium" material="ice" x="2.41" y="-1.15" rotation="90" />
<Block type="RectMedium" material="ice" x="2.72" y="-1.15" rotation="90" />
<Block type="SquareHole" material="ice" x="-2.41" y="0.11" rotation="0" />
<Block type="SquareHole" material="ice" x="-1.47" y="0.11" rotation="0" />
<Block type="SquareHole" material="wood" x="-0.53" y="0.11" rotation="0" />
<Block type="SquareHole" material="stone" x="0.53" y="0.11" rotation="0" />
<Block type="SquareHole" material="stone" x="1.47" y="0.11" rotation="0" />
<Block type="SquareHole" material="stone" x="2.41" y="0.11" rotation="0" />
<Block type="SquareHole" material="wood" x="-2.1" y="0.95" rotation="0" />
<Block type="SquareHole" material="ice" x="-0.84" y="0.95" rotation="0" />
<Block type="SquareHole" material="wood" x="0.84" y="0.95" rotation="0" />
<Block type="SquareHole" material="wood" x="2.1" y="0.95" rotation="0" />
<Pig type="BasicSmall" material="" x="2.1" y="1.62" rotation="0" />
<Pig type="BasicSmall" material="" x="1.12" y="1.62" rotation="0" />
<Pig type="BasicSmall" material="" x="-1.12" y="1.62" rotation="0" />
<Pig type="BasicSmall" material="" x="-1.82" y="1.62" rotation="0" />
</GameObjects>
</Level>

