<?xml version="1.0" encoding="utf-8"?>
<Level width ="2">
<Camera x="0" y="0" minWidth="20" maxWidth="30"/><Birds>
<Bird type="BirdBlack"/>
<Bird type="BirdBlue"/>
<Bird type="BirdRed"/>
</Birds>
<Slingshot x="-8" y="-2.5"/>
<GameObjects>
<Block type="RectTiny" material="wood" x="-2.19" y="-3.39" rotation="0" />
<Block type="RectTiny" material="stone" x="-1.27" y="-3.39" rotation="0" />
<Block type="RectTiny" material="stone" x="-0.35" y="-3.39" rotation="0" />
<Block type="RectTiny" material="stone" x="0.35" y="-3.39" rotation="0" />
<Block type="RectTiny" material="stone" x="1.27" y="-3.39" rotation="0" />
<Block type="RectTiny" material="ice" x="2.19" y="-3.39" rotation="0" />
<Block type="RectTiny" material="stone" x="-2.19" y="-3.17" rotation="0" />
<Block type="RectTiny" material="ice" x="-1.27" y="-3.17" rotation="0" />
<Block type="RectTiny" material="wood" x="-0.35" y="-3.17" rotation="0" />
<Block type="RectTiny" material="ice" x="0.35" y="-3.17" rotation="0" />
<Block type="RectTiny" material="wood" x="1.27" y="-3.17" rotation="0" />
<Block type="RectTiny" material="wood" x="2.19" y="-3.17" rotation="0" />
<Block type="RectFat" material="wood" x="-2.19" y="-2.635" rotation="90" />
<Block type="RectFat" material="wood" x="-1.27" y="-2.635" rotation="90" />
<Block type="RectFat" material="stone" x="-0.35" y="-2.635" rotation="90" />
<Block type="RectFat" material="stone" x="0.35" y="-2.635" rotation="90" />
<Block type="RectFat" material="wood" x="1.27" y="-2.635" rotation="90" />
<Block type="RectFat" material="ice" x="2.19" y="-2.635" rotation="90" />
<Block type="RectFat" material="ice" x="-2.19" y="-1.785" rotation="90" />
<Block type="RectFat" material="wood" x="-1.27" y="-1.785" rotation="90" />
<Block type="RectFat" material="wood" x="-0.35" y="-1.785" rotation="90" />
<Block type="RectFat" material="wood" x="0.35" y="-1.785" rotation="90" />
<Block type="RectFat" material="ice" x="1.27" y="-1.785" rotation="90" />
<Block type="RectFat" material="wood" x="2.19" y="-1.785" rotation="90" />
<Block type="RectFat" material="stone" x="-2.19" y="-0.935" rotation="90" />
<Block type="RectFat" material="wood" x="-1.27" y="-0.935" rotation="90" />
<Block type="RectFat" material="stone" x="-0.35" y="-0.935" rotation="90" />
<Block type="RectFat" material="wood" x="0.35" y="-0.935" rotation="90" />
<Block type="RectFat" material="stone" x="1.27" y="-0.935" rotation="90" />
<Block type="RectFat" material="stone" x="2.19" y="-0.935" rotation="90" />
<Block type="SquareSmall" material="stone" x="-2.19" y="-0.295" rotation="0" />
<Block type="SquareSmall" material="stone" x="-1.27" y="-0.295" rotation="0" />
<Block type="SquareSmall" material="wood" x="-0.35" y="-0.295" rotation="0" />
<Block type="SquareSmall" material="ice" x="0.35" y="-0.295" rotation="0" />
<Block type="SquareSmall" material="wood" x="1.27" y="-0.295" rotation="0" />
<Block type="SquareSmall" material="wood" x="2.19" y="-0.295" rotation="0" />
<Block type="RectTiny" material="stone" x="-2.19" y="0.03" rotation="0" />
<Block type="RectTiny" material="stone" x="-1.27" y="0.03" rotation="0" />
<Block type="RectTiny" material="stone" x="-0.35" y="0.03" rotation="0" />
<Block type="RectTiny" material="ice" x="0.35" y="0.03" rotation="0" />
<Block type="RectTiny" material="ice" x="1.27" y="0.03" rotation="0" />
<Block type="RectTiny" material="ice" x="2.19" y="0.03" rotation="0" />
<Block type="SquareSmall" material="stone" x="-2.19" y="0.355" rotation="0" />
<Block type="SquareSmall" material="stone" x="-1.27" y="0.355" rotation="0" />
<Block type="SquareSmall" material="stone" x="-0.35" y="0.355" rotation="0" />
<Block type="SquareSmall" material="wood" x="0.35" y="0.355" rotation="0" />
<Block type="SquareSmall" material="wood" x="1.27" y="0.355" rotation="0" />
<Block type="SquareSmall" material="stone" x="2.19" y="0.355" rotation="0" />
<Block type="RectTiny" material="wood" x="-2.19" y="0.785" rotation="90" />
<Block type="RectTiny" material="wood" x="-1.27" y="0.785" rotation="90" />
<Block type="RectTiny" material="wood" x="-0.35" y="0.785" rotation="90" />
<Block type="RectTiny" material="ice" x="0.35" y="0.785" rotation="90" />
<Block type="RectTiny" material="ice" x="1.27" y="0.785" rotation="90" />
<Block type="RectTiny" material="wood" x="2.19" y="0.785" rotation="90" />
<Block type="RectBig" material="ice" x="-1.27" y="1.11" rotation="0" />
<Block type="RectBig" material="stone" x="1.27" y="1.11" rotation="0" />
<Pig type="BasicSmall" material="" x="0.5833333333" y="1.47" rotation="0" />
<TNT type="" material="" x="-1.9566666667" y="1.47" rotation="0" />
</GameObjects>
</Level>

